<annotation>
	<folder>collectedimages</folder>
	<filename>agree.71b738b1-d2f3-11ee-ba6b-106fd9b51710.jpg</filename>
	<path>F:\Git\HearLink\HearLink\ML\RealTimeObjectDetection\Tensorflow\workspace\images\collectedimages\agree.71b738b1-d2f3-11ee-ba6b-106fd9b51710.jpg</path>
	<source>
		<database>Unknown</database>
	</source>
	<size>
		<width>640</width>
		<height>480</height>
		<depth>3</depth>
	</size>
	<segmented>0</segmented>
	<object>
		<name>Agree</name>
		<pose>Unspecified</pose>
		<truncated>0</truncated>
		<difficult>0</difficult>
		<bndbox>
			<xmin>55</xmin>
			<ymin>220</ymin>
			<xmax>170</xmax>
			<ymax>437</ymax>
		</bndbox>
	</object>
</annotation>
